odoo/addons/delivery_carrier_multi_zip/README.rst
odoo/addons/delivery_carrier_multi_zip/__init__.py
odoo/addons/delivery_carrier_multi_zip/__manifest__.py
odoo/addons/delivery_carrier_multi_zip/i18n/de.po
odoo/addons/delivery_carrier_multi_zip/i18n/delivery_carrier_multi_zip.pot
odoo/addons/delivery_carrier_multi_zip/i18n/es.po
odoo/addons/delivery_carrier_multi_zip/i18n/it.po
odoo/addons/delivery_carrier_multi_zip/models/__init__.py
odoo/addons/delivery_carrier_multi_zip/models/delivery_carrier.py
odoo/addons/delivery_carrier_multi_zip/readme/CONFIGURE.md
odoo/addons/delivery_carrier_multi_zip/readme/CONTRIBUTORS.md
odoo/addons/delivery_carrier_multi_zip/readme/DESCRIPTION.md
odoo/addons/delivery_carrier_multi_zip/security/ir.model.access.csv
odoo/addons/delivery_carrier_multi_zip/static/description/icon.png
odoo/addons/delivery_carrier_multi_zip/static/description/index.html
odoo/addons/delivery_carrier_multi_zip/tests/__init__.py
odoo/addons/delivery_carrier_multi_zip/tests/test_delivery_carrier_multi_zip.py
odoo/addons/delivery_carrier_multi_zip/views/delivery_carrier_view.xml
odoo_addon_delivery_carrier_multi_zip-17.0.1.0.0.4.dist-info/METADATA
odoo_addon_delivery_carrier_multi_zip-17.0.1.0.0.4.dist-info/WHEEL
odoo_addon_delivery_carrier_multi_zip-17.0.1.0.0.4.dist-info/top_level.txt
odoo_addon_delivery_carrier_multi_zip-17.0.1.0.0.4.dist-info/RECORD
